mkdocs_include_markdown_plugin/__init__.py
mkdocs_include_markdown_plugin/cache.py
mkdocs_include_markdown_plugin/config.py
mkdocs_include_markdown_plugin/directive.py
mkdocs_include_markdown_plugin/event.py
mkdocs_include_markdown_plugin/files_watcher.py
mkdocs_include_markdown_plugin/logger.py
mkdocs_include_markdown_plugin/placeholders.py
mkdocs_include_markdown_plugin/plugin.py
mkdocs_include_markdown_plugin/process.py
mkdocs_include_markdown_plugin/py.typed
mkdocs_include_markdown_plugin-7.2.1.dist-info/METADATA
mkdocs_include_markdown_plugin-7.2.1.dist-info/WHEEL
mkdocs_include_markdown_plugin-7.2.1.dist-info/entry_points.txt
mkdocs_include_markdown_plugin-7.2.1.dist-info/licenses/LICENSE
mkdocs_include_markdown_plugin-7.2.1.dist-info/RECORD
