Metadata-Version: 2.4
Name: mkdocs-include-markdown-plugin
Version: 7.2.1
Summary: Mkdocs Markdown includer plugin.
Project-URL: Source, https://github.com/mondeja/mkdocs-include-markdown-plugin
Project-URL: Documentation, https://github.com/mondeja/mkdocs-include-markdown-plugin#documentation
Project-URL: Bug tracker, https://github.com/mondeja/mkdocs-include-markdown-plugin/issues
Project-URL: Changelog, https://github.com/mondeja/mkdocs-include-markdown-plugin/releases
Author: Joe Rickerby
Author-email: Álvaro Mondéjar Rubio <mondejar1994@gmail.com>
Maintainer-email: Álvaro Mondéjar Rubio <mondejar1994@gmail.com>
License-Expression: Apache-2.0
License-File: LICENSE
Keywords: includer,markdown,mkdocs,plugin
Classifier: Development Status :: 5 - Production/Stable
Classifier: Environment :: Console
Classifier: Intended Audience :: Developers
Classifier: License :: OSI Approved :: Apache Software License
Classifier: Operating System :: OS Independent
Classifier: Programming Language :: Python :: 3.9
Classifier: Programming Language :: Python :: 3.10
Classifier: Programming Language :: Python :: 3.11
Classifier: Programming Language :: Python :: 3.12
Classifier: Programming Language :: Python :: 3.13
Classifier: Topic :: Documentation
Classifier: Topic :: Software Development :: Documentation
Classifier: Topic :: Text Processing
Classifier: Topic :: Text Processing :: Markup :: Markdown
Requires-Python: >=3.9
Requires-Dist: mkdocs>=1.4
Requires-Dist: wcmatch
Provides-Extra: cache
Requires-Dist: platformdirs; extra == 'cache'
